{
  "colors": [
    {
      "id": 1,
      "name": "Navy",
      "src": "navy.avif",
      "code": "#1d1e3a"
    },
    {
      "id": 2,
      "name": "DEEP REEF",
      "src": "DEEPREEF.avif",
      "code": "#012A4A"
    },
    {
      "id": 3,
      "name": "Black",
      "src": "black.avif",
      "code": "#101010"
    },
    {
      "id": 4,
      "name": "Royal blue",
      "src": "royalBlue.avif",
      "code": "#006EE7"
    },
    {
      "id": 5,
      "name": "Moss",
      "src": "Moss.avif",
      "code": "#4C564B"
    },
    {
      "id": 6,
      "name": "CEIL BLUE",
      "src": "CEILBLUE.avif",
      "code": "#7CB4E7"
    },
    {
      "id": 7,
      "name": "Carousel",
      "src": "Carousel.avif",
      "code": "#48474C"
    },
    {
      "id": 8,
      "name": "Pink Sand",
      "src": "PinkSand.avif",
      "code": "#E7BFBD"
    },
    {
      "id": 9,
      "name": "Earth",
      "src": "Earth.webp",
      "code": "#835731"
    },
    {
      "id": 10,
      "name": "Hunter green",
      "src": "Hunter_Green.avif",
      "code": "#004E3E"
    }
  ]
}
